async_shell/__init__.py
async_shell/constants.py
async_shell/py.typed
async_shell/version.py
async_shell-1.1.0.dist-info/LICENSE
async_shell-1.1.0.dist-info/METADATA
async_shell-1.1.0.dist-info/WHEEL
async_shell-1.1.0.dist-info/RECORD
